setup.py
django_jcache.egg-info/PKG-INFO
django_jcache.egg-info/SOURCES.txt
django_jcache.egg-info/dependency_links.txt
django_jcache.egg-info/requires.txt
django_jcache.egg-info/top_level.txt
jcache/__init__.py
jcache/models.py
jcache/tests.py