Metadata-Version: 1.0
Name: django-jcache
Version: 0.6
Summary: JCache support for Django
Home-page: UNKNOWN
Author: James Aylett
Author-email: james@tartarus.org
License: MIT
Platform: UNKNOWN
Classifier: Intended Audience :: Developers
Classifier: Framework :: Django
Classifier: License :: OSI Approved :: MIT License
Classifier: Programming Language :: Python :: 2
